LICENSE
README.md
setup.py
Skoal.egg-info/PKG-INFO
Skoal.egg-info/SOURCES.txt
Skoal.egg-info/dependency_links.txt
Skoal.egg-info/entry_points.txt
Skoal.egg-info/requires.txt
Skoal.egg-info/top_level.txt
skoal/Fermi_handler.py
skoal/GCN_utils.py
skoal/Multiscope_handler.py
skoal/__init__.py
skoal/config_utils.py
skoal/faster_fieldfinder.py
skoal/fastest_fieldfinder.py
skoal/field_from_coords.py
skoal/lvc_handler.py
skoal/main.py
skoal/paths.py
skoal/scheduler_utilities.py
skoal/tesselation_generator.py
skoal/data/configs/Bennyscope.cfg
skoal/data/configs/Borderscope.cfg
skoal/data/configs/RASA11.cfg
skoal/data/configs/ZTF.cfg
skoal/data/configs/default.cfg
skoal/data/skymaps/MS240324c_3_bayestar.multiorder.fits,1
skoal/data/skymaps/MS240324x_3_bayestar.multiorder.fits,1
skoal/data/skymaps/S240603ar_2_bayestar.multiorder.fits,1
skoal/data/skymaps/S240603n_2_cwb.multiorder.fits,1
skoal/data/skymaps/S240605a_2_bayestar.multiorder.fits,1
skoal/data/tesselations/RASA11.tess
skoal/data/tesselations/kasa11.tess
skoal/data/test_eventfiles/gcn.classic.voevent.FERMI_GBM_POS_TEST_4581.xml
skoal/data/test_eventfiles/gcn.classic.voevent.FERMI_GBM_POS_TEST_4586.xml
skoal/data/test_eventfiles/gcn.classic.voevent.LVC_INITIAL_7486.xml
skoal/data/test_eventfiles/gcn.classic.voevent.LVC_INITIAL_7496.xml