Metadata-Version: 2.1
Name: Skoal
Version: 0.422
Summary: a kilonova followup scheduling package for fermi and lvc notices
Home-page: https://github.com/borderbenja05/skoal
Author: Benny Border
Author-email: borderbenja@gmail.com
Classifier: Programming Language :: Python :: 3
Classifier: License :: OSI Approved :: MIT License
Classifier: Operating System :: OS Independent
Requires-Python: >=3.6
License-File: LICENSE
Requires-Dist: numpy
Requires-Dist: scikit-learn
Requires-Dist: astropy
Requires-Dist: astropy-healpix
Requires-Dist: astroplan
Requires-Dist: scipy
Requires-Dist: argparse
Requires-Dist: configparser
Requires-Dist: requests
Requires-Dist: ligo-gracedb>=2.10.0
Requires-Dist: lxml
Requires-Dist: urllib3>=2.1.0
